README.rst
setup.cfg
setup.py
basiqrapid/APIError.py
basiqrapid/Expense.py
basiqrapid/Income.py
basiqrapid/Job.py
basiqrapid/__init__.py
basiqrapid/main.py
basiqrapid/util.py
basiqrapid.egg-info/PKG-INFO
basiqrapid.egg-info/SOURCES.txt
basiqrapid.egg-info/dependency_links.txt
basiqrapid.egg-info/requires.txt
basiqrapid.egg-info/top_level.txt