Metadata-Version: 1.1
Name: basiqrapid
Version: 1.0.8
Summary: A Python wrapper for Basiq.io's API
Home-page: https://github.com/mike-gee/basiqrapid
Author: Michael Gee
Author-email: michael.gee2018@gmail.com
License: MIT
Download-URL: https://github.com/mike-gee/basiqrapid/archive/v_01.tar.gz
Keywords: basiq,finance,sdk,api,python,wrapper
Platform: UNKNOWN
Classifier: Topic :: Utilities
